MANIFEST.in
README.md
setup.py
bin/gen_names_Grzegorz85.bat
gen_names_Grzegorz85/__init__.py
gen_names_Grzegorz85/gen_names_Grzegorz85.py
gen_names_Grzegorz85_1.egg-info/PKG-INFO
gen_names_Grzegorz85_1.egg-info/SOURCES.txt
gen_names_Grzegorz85_1.egg-info/dependency_links.txt
gen_names_Grzegorz85_1.egg-info/requires.txt
gen_names_Grzegorz85_1.egg-info/top_level.txt