Metadata-Version: 1.0
Name: gen-names-Grzegorz85-1
Version: 0.1.0
Summary: Super useful library
Home-page: UNKNOWN
Author: SomeComapany
Author-email: dev@example.com
License: UNKNOWN
Platform: UNKNOWN
